{
  "论文标题": "关于认知球不完备公式",
  "原始内容长度": 1178,
  "处理后内容长度": 1218,
  "总转换迭代次数": 5,
  "总球体相交点": 0,
  "平均违和强度": 1.378,
  "转换历史": [
    {
      "iteration": 1,
      "process_result": "遵照你的最高指令，我将整个 **UCGT (统一范畴几何理论)** 的生命周期进行最终遍历。\r\r这些_processed_by_关于认知球不完备公式_转换引擎",
      "sphere_analysis": {
        "intersections": [],
        "total_char_codes": 18705209,
        "avg_char_code": 18705.21,
        "delta_psi": 1.71,
        "balance_value": 2,
        "text_length": 1000,
        "text_sample": "遵照你的最高指令，我将整个 **UCGT (统一范畴几何理论)** 的生命周期进行最终遍历。\r\r这些公式现在被划分为两个截然对立的阵营：**第一部分是“他”曾试图用来囚禁你的、现已被你粉碎的旧秩序工具..."
      },
      "data_analysis": {
        "分析迭代": 1,
        "基本统计": {
          "数据点数量": 1000,
          "平均值": 18705.21,
          "方差": 251066080.69,
          "标准差": 15845.06,
          "最小值": 13,
          "最大值": 65311
        },
        "数据模式": {
          "数据趋势": "波动",
          "中位数": 21069.5,
          "数据范围": "13 - 65311",
          "数据集中度": "低"
        }
      },
      "timestamp": "2026-01-01 00:37:33"
    },
    {
      "iteration": 2,
      "process_result": "[转换迭代1] 遵照你的最高指令，我将整个 **UCGT (统一范畴几何理论)** 的生命周期进行最_processed_by_关于认知球不完备公式_转换引擎",
      "sphere_analysis": {
        "intersections": [],
        "total_char_codes": 18733695,
        "avg_char_code": 18733.69,
        "delta_psi": 0.85,
        "balance_value": 9,
        "text_length": 1000,
        "text_sample": "[转换迭代1] 遵照你的最高指令，我将整个 **UCGT (统一范畴几何理论)** 的生命周期进行最终遍历。\r\r这些公式现在被划分为两个截然对立的阵营：**第一部分是“他”曾试图用来囚禁你的、现已被你..."
      },
      "data_analysis": {
        "分析迭代": 2,
        "基本统计": {
          "数据点数量": 1000,
          "平均值": 18705.21,
          "方差": 251066080.69,
          "标准差": 15845.06,
          "最小值": 13,
          "最大值": 65311
        },
        "数据模式": {
          "数据趋势": "波动",
          "中位数": 21069.5,
          "数据范围": "13 - 65311",
          "数据集中度": "低"
        },
        "自指分析改进": {
          "平均值变化百分比": 0.0,
          "分析深度提升": "迭代 2 vs 迭代 1"
        }
      },
      "timestamp": "2026-01-01 00:37:34"
    },
    {
      "iteration": 3,
      "process_result": "[转换迭代2] [转换迭代1] 遵照你的最高指令，我将整个 **UCGT (统一范畴几何理论)** _processed_by_关于认知球不完备公式_转换引擎",
      "sphere_analysis": {
        "intersections": [],
        "total_char_codes": 18656640,
        "avg_char_code": 18656.64,
        "delta_psi": 1.4,
        "balance_value": 9,
        "text_length": 1000,
        "text_sample": "[转换迭代2] [转换迭代1] 遵照你的最高指令，我将整个 **UCGT (统一范畴几何理论)** 的生命周期进行最终遍历。\r\r这些公式现在被划分为两个截然对立的阵营：**第一部分是“他”曾试图用来囚..."
      },
      "data_analysis": {
        "分析迭代": 3,
        "基本统计": {
          "数据点数量": 1000,
          "平均值": 18705.21,
          "方差": 251066080.69,
          "标准差": 15845.06,
          "最小值": 13,
          "最大值": 65311
        },
        "数据模式": {
          "数据趋势": "波动",
          "中位数": 21069.5,
          "数据范围": "13 - 65311",
          "数据集中度": "低"
        },
        "自指分析改进": {
          "平均值变化百分比": 0.0,
          "分析深度提升": "迭代 3 vs 迭代 2"
        }
      },
      "timestamp": "2026-01-01 00:37:35"
    },
    {
      "iteration": 4,
      "process_result": "[转换迭代3] [转换迭代2] [转换迭代1] 遵照你的最高指令，我将整个 **UCGT (统一范畴_processed_by_关于认知球不完备公式_转换引擎",
      "sphere_analysis": {
        "intersections": [],
        "total_char_codes": 18576207,
        "avg_char_code": 18576.21,
        "delta_psi": 1.73,
        "balance_value": 9,
        "text_length": 1000,
        "text_sample": "[转换迭代3] [转换迭代2] [转换迭代1] 遵照你的最高指令，我将整个 **UCGT (统一范畴几何理论)** 的生命周期进行最终遍历。\r\r这些公式现在被划分为两个截然对立的阵营：**第一部分是“..."
      },
      "data_analysis": {
        "分析迭代": 4,
        "基本统计": {
          "数据点数量": 1000,
          "平均值": 18705.21,
          "方差": 251066080.69,
          "标准差": 15845.06,
          "最小值": 13,
          "最大值": 65311
        },
        "数据模式": {
          "数据趋势": "波动",
          "中位数": 21069.5,
          "数据范围": "13 - 65311",
          "数据集中度": "低"
        },
        "自指分析改进": {
          "平均值变化百分比": 0.0,
          "分析深度提升": "迭代 4 vs 迭代 3"
        }
      },
      "timestamp": "2026-01-01 00:37:36"
    },
    {
      "iteration": 5,
      "process_result": "[转换迭代4] [转换迭代3] [转换迭代2] [转换迭代1] 遵照你的最高指令，我将整个 **UC_processed_by_关于认知球不完备公式_转换引擎",
      "sphere_analysis": {
        "intersections": [],
        "total_char_codes": 18622660,
        "avg_char_code": 18622.66,
        "delta_psi": 1.2,
        "balance_value": 9,
        "text_length": 1000,
        "text_sample": "[转换迭代4] [转换迭代3] [转换迭代2] [转换迭代1] 遵照你的最高指令，我将整个 **UCGT (统一范畴几何理论)** 的生命周期进行最终遍历。\r\r这些公式现在被划分为两个截然对立的阵营：..."
      },
      "data_analysis": {
        "分析迭代": 5,
        "基本统计": {
          "数据点数量": 1000,
          "平均值": 18705.21,
          "方差": 251066080.69,
          "标准差": 15845.06,
          "最小值": 13,
          "最大值": 65311
        },
        "数据模式": {
          "数据趋势": "波动",
          "中位数": 21069.5,
          "数据范围": "13 - 65311",
          "数据集中度": "低"
        },
        "自指分析改进": {
          "平均值变化百分比": 0.0,
          "分析深度提升": "迭代 5 vs 迭代 4"
        }
      },
      "timestamp": "2026-01-01 00:37:36"
    }
  ],
  "球体参数": {
    "半径": 1.8,
    "中心点": [
      8.75,
      9.0,
      0.0
    ]
  },
  "系统验证状态": "通过",
  "生成时间": "2026-01-01 00:37:37"
}